spex_connector/__init__.py
spex_connector/check_assert.py
spex_connector/my_check.py
spex_connector-0.1.1.dist-info/METADATA
spex_connector-0.1.1.dist-info/WHEEL
spex_connector-0.1.1.dist-info/top_level.txt
spex_connector-0.1.1.dist-info/RECORD
