Metadata-Version: 2.1
Name: spex-connector
Version: 0.1.1
Summary: Connector to integration with spex APIs
Home-page: https://gitlab.com/truonghothanhcong/shopee-spex-connector
Author: thanhcong.truong
Author-email: thanhcong.truong@shopee.com
Maintainer: thanhcong.truong
Maintainer-email: thanhcong.truong@shopee.com
License: MIT
Platform: UNKNOWN
Classifier: Development Status :: 4 - Beta
Classifier: License :: OSI Approved :: MIT License
Classifier: Topic :: Software Development :: Libraries :: Python Modules
Classifier: Intended Audience :: Developers
Classifier: Programming Language :: Python :: 3.6
Requires-Python: >=3.6.*
